MANIFEST.in
README.md
setup.py
python_shorturl.egg-info/PKG-INFO
python_shorturl.egg-info/SOURCES.txt
python_shorturl.egg-info/dependency_links.txt
python_shorturl.egg-info/not-zip-safe
python_shorturl.egg-info/top_level.txt
shorturlpy/__init__.py
shorturlpy/shorturlpy.py