Metadata-Version: 1.1
Name: python-shorturl
Version: 0.0.4
Summary: Python url shortner library for tinyurl.com, is.gd and bit.ly
Home-page: https://github.com/appscluster/python-shorturl
Author: Abdul Hamid
Author-email: ap@appscluster.com
License: MIT
Download-URL: https://github.com/appscluster/python-shorturl/archive/master.zip
Keywords: tinyurl,shorturl,utility,bitly,is.gd
Platform: OS Independent
Classifier: Topic :: Utilities
Classifier: Environment :: Web Environment
Classifier: Development Status :: 4 - Beta
Classifier: Intended Audience :: Developers
Classifier: Operating System :: OS Independent
Classifier: Programming Language :: Python :: 2.7
